epldata
