Metadata-Version: 2.1
Name: epldata
Version: 0.3.4
Summary: Stuff
Home-page: UNKNOWN
Author: Sarang Purandare
Author-email: purandare.sarang@gmail.com
License: UNKNOWN
Platform: UNKNOWN
Classifier: Programming Language :: Python :: 3
